README.md
setup.cfg
setup.py
Printlog.egg-info/PKG-INFO
Printlog.egg-info/SOURCES.txt
Printlog.egg-info/dependency_links.txt
Printlog.egg-info/top_level.txt
printlog/__init__.py
printlog/color.py
printlog/log.py
printlog/utils.py
printlog.egg-info/PKG-INFO
printlog.egg-info/SOURCES.txt
printlog.egg-info/dependency_links.txt
printlog.egg-info/top_level.txt