Metadata-Version: 2.1
Name: printlog
Version: 0.0.5
Summary: Colorize your logs to spot them at a glance.
Home-page: https://github.com/LudovicPatho/printlog
Author: Patho Ludovic
Author-email: ludovic.patho@gmail.com
Maintainer: Ludovic Patho
Maintainer-email: ludovic.patho@gmail.com
License: GPL V3
Keywords: colour print log
Platform: ALL
Classifier: Topic :: Utilities
Classifier: Topic :: Software Development :: Bug Tracking
Classifier: Topic :: Software Development :: Debuggers
